fraction/Fraction.py
fraction/__init__.py
Fraction-2.2.0.dist-info/LICENSE
Fraction-2.2.0.dist-info/METADATA
Fraction-2.2.0.dist-info/WHEEL
Fraction-2.2.0.dist-info/top_level.txt
Fraction-2.2.0.dist-info/RECORD
