Metadata-Version: 2.1
Name: Fraction
Version: 2.2.0
Summary: Fraction carries out all the fraction operations including addition, subtraction, multiplication, division, reciprocation
Home-page: https://github.com/bradley101/fraction
Author: Shantanu Banerjee
Author-email: hi@shantanubanerjee.com
Classifier: Programming Language :: Python :: 3
Classifier: License :: OSI Approved :: MIT License
Classifier: Operating System :: OS Independent
Classifier: Topic :: Scientific/Engineering :: Mathematics
License-File: LICENSE
